clarivate/__init__.py
clarivate/txt2json.py
pyunit_clarivate-2025.5.2.dist-info/METADATA
pyunit_clarivate-2025.5.2.dist-info/WHEEL
pyunit_clarivate-2025.5.2.dist-info/top_level.txt
pyunit_clarivate-2025.5.2.dist-info/zip-safe
pyunit_clarivate-2025.5.2.dist-info/RECORD
